emqx_mcp_server/__init__.py
emqx_mcp_server/config.py
emqx_mcp_server/emqx_client.py
emqx_mcp_server/server.py
emqx_mcp_server/tools/__init__.py
emqx_mcp_server/tools/emqx_client_tools.py
emqx_mcp_server/tools/emqx_message_tools.py
iflow_mcp_benniu_emqx_mcp_server-0.1.0.dist-info/METADATA
iflow_mcp_benniu_emqx_mcp_server-0.1.0.dist-info/WHEEL
iflow_mcp_benniu_emqx_mcp_server-0.1.0.dist-info/entry_points.txt
iflow_mcp_benniu_emqx_mcp_server-0.1.0.dist-info/licenses/LICENSE
iflow_mcp_benniu_emqx_mcp_server-0.1.0.dist-info/RECORD
